{
  "main": {
    "id": "3dd53b8250467576",
    "type": "split",
    "children": [
      {
        "id": "d909c4ac9055dd77",
        "type": "tabs",
        "children": [
          {
            "id": "54008922cfa406bb",
            "type": "leaf",
            "state": {
              "type": "markdown",
              "state": {
                "file": "CyberSec/Theory/Linux/Linux Command Line.md",
                "mode": "source",
                "backlinks": false,
                "source": true
              }
            }
          }
        ]
      }
    ],
    "direction": "vertical"
  },
  "left": {
    "id": "faf2db552574aca6",
    "type": "split",
    "children": [
      {
        "id": "a95cd082976af948",
        "type": "tabs",
        "children": [
          {
            "id": "737d055bac789dfd",
            "type": "leaf",
            "state": {
              "type": "file-explorer",
              "state": {
                "sortOrder": "alphabetical"
              }
            }
          },
          {
            "id": "7b2d1357535fcfe0",
            "type": "leaf",
            "state": {
              "type": "search",
              "state": {
                "query": "ssh",
                "matchingCase": false,
                "explainSearch": false,
                "collapseAll": false,
                "extraContext": false,
                "sortOrder": "alphabetical"
              }
            }
          }
        ]
      }
    ],
    "direction": "horizontal",
    "width": 300,
    "collapsed": true
  },
  "right": {
    "id": "01559e3f5c72e717",
    "type": "split",
    "children": [],
    "direction": "horizontal",
    "width": 300,
    "collapsed": true
  },
  "active": "54008922cfa406bb",
  "lastOpenFiles": [
    "CyberSec/Tools/test.md",
    "CyberSec/Theory/Programming Languages/Bash/Intro.md",
    "CyberSec/Theory/Linux/File System.md",
    "CyberSec/Theory/Programming Languages/Bash/Loops.md",
    "CyberSec/Theory/Programming Languages/Bash/Conditions.md",
    "CyberSec/Theory/Linux/Linux Command Line.md",
    "CyberSec/Tools/Regular Expression.md",
    "CyberSec/Tools/sed.md",
    "CyberSec/Tools/Vim.md",
    "CyberSec/Theory/Linux/How does shell work.md"
  ]
}